{
  "version": "1.0.0",
  "sourcePassageVoice": "passage-voice.card#v3.0.0",
  "sourceAudio": "passage-voice-3.0.0.flac",
  "duration": null,
  "words": [
    {
      "word": "The",
      "start": 0,
      "end": 0.14000000059604645,
      "aligned": true
    },
    {
      "word": "freighter",
      "start": 0.14000000059604645,
      "end": 0.6000000238418579,
      "aligned": true
    },
    {
      "word": "appears",
      "start": 0.6000000238418579,
      "end": 0.9399999976158142,
      "aligned": true
    },
    {
      "word": "in",
      "start": 0.9399999976158142,
      "end": 1.1399999856948853,
      "aligned": true
    },
    {
      "word": "the",
      "start": 1.1399999856948853,
      "end": 1.340000033378601,
      "aligned": true
    },
    {
      "word": "sky",
      "start": 1.340000033378601,
      "end": 1.6399999856948853,
      "aligned": true
    },
    {
      "word": "just",
      "start": 1.6399999856948853,
      "end": 2.240000009536743,
      "aligned": true
    },
    {
      "word": "after",
      "start": 2.240000009536743,
      "end": 2.7200000286102295,
      "aligned": true
    },
    {
      "word": "dawn.",
      "start": 2.7200000286102295,
      "end": 3.119999885559082,
      "aligned": true
    },
    {
      "word": "I'm",
      "start": 3.740000009536743,
      "end": 3.8399999141693115,
      "aligned": true
    },
    {
      "word": "standing",
      "start": 3.8399999141693115,
      "end": 4.079999923706055,
      "aligned": true
    },
    {
      "word": "outside",
      "start": 4.079999923706055,
      "end": 4.460000038146973,
      "aligned": true
    },
    {
      "word": "the",
      "start": 4.460000038146973,
      "end": 4.699999809265137,
      "aligned": true
    },
    {
      "word": "facility",
      "start": 4.699999809265137,
      "end": 4.980000019073486,
      "aligned": true
    },
    {
      "word": "with",
      "start": 4.980000019073486,
      "end": 5.639999866485596,
      "aligned": true
    },
    {
      "word": "Scout,",
      "start": 5.639999866485596,
      "end": 5.639999866485596,
      "aligned": true
    },
    {
      "word": "watching",
      "start": 6.139999866485596,
      "end": 6.480000019073486,
      "aligned": true
    },
    {
      "word": "it",
      "start": 6.480000019073486,
      "end": 6.760000228881836,
      "aligned": true
    },
    {
      "word": "descend.",
      "start": 6.760000228881836,
      "end": 7.079999923706055,
      "aligned": true
    },
    {
      "word": "The",
      "start": 7.760000228881836,
      "end": 7.820000171661377,
      "aligned": true
    },
    {
      "word": "whole",
      "start": 7.820000171661377,
      "end": 8.15999984741211,
      "aligned": true
    },
    {
      "word": "community",
      "start": 8.15999984741211,
      "end": 8.4399995803833,
      "aligned": true
    },
    {
      "word": "is",
      "start": 8.4399995803833,
      "end": 9.079999923706055,
      "aligned": true
    },
    {
      "word": "gathered—not",
      "start": 9.079999923706055,
      "end": 9.739999771118164,
      "aligned": false
    },
    {
      "word": "crowding,",
      "start": 9.739999771118164,
      "end": 10,
      "aligned": true
    },
    {
      "word": "just…",
      "start": 10.319999694824219,
      "end": 10.65999984741211,
      "aligned": true
    },
    {
      "word": "present—supporting",
      "start": 10.65999984741211,
      "end": 11.960000038146973,
      "aligned": false
    },
    {
      "word": "me,",
      "start": 11.960000038146973,
      "end": 12.380000114440918,
      "aligned": true
    },
    {
      "word": "whatever",
      "start": 12.380000114440918,
      "end": 12.9399995803833,
      "aligned": true
    },
    {
      "word": "happens.",
      "start": 12.9399995803833,
      "end": 13.479999542236328,
      "aligned": true
    },
    {
      "word": "Scout",
      "start": 14.260000228881836,
      "end": 14.279999732971191,
      "aligned": true
    },
    {
      "word": "bounces,",
      "start": 14.279999732971191,
      "end": 14.65999984741211,
      "aligned": true
    },
    {
      "word": "nervous-excited—big",
      "start": 14.65999984741211,
      "end": 16.260000228881836,
      "aligned": false
    },
    {
      "word": "moment",
      "start": 16.260000228881836,
      "end": 16.540000915527344,
      "aligned": true
    },
    {
      "word": "bounce.",
      "start": 16.540000915527344,
      "end": 16.8799991607666,
      "aligned": true
    },
    {
      "word": "I",
      "start": 17.34000015258789,
      "end": 17.579999923706055,
      "aligned": true
    },
    {
      "word": "say,",
      "start": 17.579999923706055,
      "end": 17.84000015258789,
      "aligned": true
    },
    {
      "word": "\"Yeah.",
      "start": 17.979999542236328,
      "end": 18.18000030517578,
      "aligned": true
    },
    {
      "word": "Big",
      "start": 18.479999542236328,
      "end": 18.760000228881836,
      "aligned": true
    },
    {
      "word": "moment.\"",
      "start": 18.760000228881836,
      "end": 19.040000915527344,
      "aligned": true
    },
    {
      "word": "The",
      "start": 19.540000915527344,
      "end": 19.799999237060547,
      "aligned": true
    },
    {
      "word": "commercial",
      "start": 19.799999237060547,
      "end": 20.18000030517578,
      "aligned": true
    },
    {
      "word": "freighter",
      "start": 20.18000030517578,
      "end": 20.700000762939453,
      "aligned": true
    },
    {
      "word": "Harmony",
      "start": 20.700000762939453,
      "end": 21,
      "aligned": true
    },
    {
      "word": "Prospect",
      "start": 21,
      "end": 21.579999923706055,
      "aligned": true
    },
    {
      "word": "lands",
      "start": 21.579999923706055,
      "end": 22.059999465942383,
      "aligned": true
    },
    {
      "word": "smoothly—a",
      "start": 22.059999465942383,
      "end": 23.299999237060547,
      "aligned": false
    },
    {
      "word": "professional",
      "start": 23.299999237060547,
      "end": 23.719999313354492,
      "aligned": true
    },
    {
      "word": "operation.",
      "start": 23.719999313354492,
      "end": 24.31999969482422,
      "aligned": true
    },
    {
      "word": "Two",
      "start": 25.059999465942383,
      "end": 25.219999313354492,
      "aligned": true
    },
    {
      "word": "figures",
      "start": 25.219999313354492,
      "end": 25.559999465942383,
      "aligned": true
    },
    {
      "word": "emerge:",
      "start": 25.559999465942383,
      "end": 26,
      "aligned": true
    },
    {
      "word": "Captain",
      "start": 26.700000762939453,
      "end": 26.799999237060547,
      "aligned": true
    },
    {
      "word": "Torres",
      "start": 26.799999237060547,
      "end": 27.079999923706055,
      "aligned": true
    },
    {
      "word": "and",
      "start": 27.079999923706055,
      "end": 27.68000030517578,
      "aligned": true
    },
    {
      "word": "a",
      "start": 27.68000030517578,
      "end": 28.100000381469727,
      "aligned": true
    },
    {
      "word": "medical",
      "start": 28.100000381469727,
      "end": 28.100000381469727,
      "aligned": true
    },
    {
      "word": "officer.",
      "start": 28.100000381469727,
      "end": 28.440000534057617,
      "aligned": true
    },
    {
      "word": "I",
      "start": 28.84000015258789,
      "end": 29.100000381469727,
      "aligned": true
    },
    {
      "word": "walk",
      "start": 29.100000381469727,
      "end": 29.479999542236328,
      "aligned": true
    },
    {
      "word": "forward",
      "start": 29.479999542236328,
      "end": 29.81999969482422,
      "aligned": true
    },
    {
      "word": "to",
      "start": 29.81999969482422,
      "end": 30.059999465942383,
      "aligned": true
    },
    {
      "word": "meet",
      "start": 30.059999465942383,
      "end": 30.18000030517578,
      "aligned": true
    },
    {
      "word": "them,",
      "start": 30.18000030517578,
      "end": 30.3799991607666,
      "aligned": true
    },
    {
      "word": "calm",
      "start": 31.1200008392334,
      "end": 31.139999389648438,
      "aligned": true
    },
    {
      "word": "and",
      "start": 31.139999389648438,
      "end": 31.479999542236328,
      "aligned": true
    },
    {
      "word": "certain.",
      "start": 31.479999542236328,
      "end": 31.68000030517578,
      "aligned": true
    },
    {
      "word": "I",
      "start": 32.040000915527344,
      "end": 32.040000915527344,
      "aligned": true
    },
    {
      "word": "say",
      "start": 32.040000915527344,
      "end": 32.279998779296875,
      "aligned": true
    },
    {
      "word": "formally,",
      "start": 32.279998779296875,
      "end": 32.7400016784668,
      "aligned": true
    },
    {
      "word": "\"Captain",
      "start": 33.52000045776367,
      "end": 33.52000045776367,
      "aligned": true
    },
    {
      "word": "Torres,",
      "start": 33.52000045776367,
      "end": 33.900001525878906,
      "aligned": true
    },
    {
      "word": "thank",
      "start": 34.13999938964844,
      "end": 34.29999923706055,
      "aligned": true
    },
    {
      "word": "you",
      "start": 34.29999923706055,
      "end": 34.41999816894531,
      "aligned": true
    },
    {
      "word": "for",
      "start": 34.41999816894531,
      "end": 34.65999984741211,
      "aligned": true
    },
    {
      "word": "coming.\"",
      "start": 34.65999984741211,
      "end": 34.86000061035156,
      "aligned": true
    },
    {
      "word": "Captain",
      "start": 35.619998931884766,
      "end": 35.779998779296875,
      "aligned": true
    },
    {
      "word": "Torres",
      "start": 35.779998779296875,
      "end": 36.099998474121094,
      "aligned": true
    },
    {
      "word": "asks,",
      "start": 36.099998474121094,
      "end": 36.560001373291016,
      "aligned": true
    },
    {
      "word": "\"Kira",
      "start": 37.119998931884766,
      "end": 37.13999938964844,
      "aligned": true
    },
    {
      "word": "Voss?",
      "start": 37.13999938964844,
      "end": 37.47999954223633,
      "aligned": true
    },
    {
      "word": "Survivor",
      "start": 38.220001220703125,
      "end": 38.220001220703125,
      "aligned": true
    },
    {
      "word": "of",
      "start": 38.220001220703125,
      "end": 38.47999954223633,
      "aligned": true
    },
    {
      "word": "courier",
      "start": 38.47999954223633,
      "end": 38.720001220703125,
      "aligned": true
    },
    {
      "word": "vessel",
      "start": 38.720001220703125,
      "end": 39,
      "aligned": true
    },
    {
      "word": "crash?\"",
      "start": 39,
      "end": 39.380001068115234,
      "aligned": true
    },
    {
      "word": "I",
      "start": 39.900001525878906,
      "end": 40.18000030517578,
      "aligned": true
    },
    {
      "word": "say,",
      "start": 40.18000030517578,
      "end": 40.31999969482422,
      "aligned": true
    },
    {
      "word": "\"That's",
      "start": 40.36000061035156,
      "end": 40.619998931884766,
      "aligned": true
    },
    {
      "word": "me.\"",
      "start": 40.619998931884766,
      "end": 40.880001068115234,
      "aligned": true
    },
    {
      "word": "Captain",
      "start": 41.459999084472656,
      "end": 41.619998931884766,
      "aligned": true
    },
    {
      "word": "Torres",
      "start": 41.619998931884766,
      "end": 41.900001525878906,
      "aligned": true
    },
    {
      "word": "says,",
      "start": 41.900001525878906,
      "end": 42.2400016784668,
      "aligned": true
    },
    {
      "word": "\"We're",
      "start": 42.5,
      "end": 42.560001373291016,
      "aligned": true
    },
    {
      "word": "here",
      "start": 42.560001373291016,
      "end": 42.779998779296875,
      "aligned": true
    },
    {
      "word": "to",
      "start": 42.779998779296875,
      "end": 43.08000183105469,
      "aligned": true
    },
    {
      "word": "extract",
      "start": 43.08000183105469,
      "end": 43.34000015258789,
      "aligned": true
    },
    {
      "word": "you",
      "start": 43.34000015258789,
      "end": 43.560001373291016,
      "aligned": true
    },
    {
      "word": "and",
      "start": 43.560001373291016,
      "end": 43.7400016784668,
      "aligned": true
    },
    {
      "word": "return",
      "start": 43.7400016784668,
      "end": 43.97999954223633,
      "aligned": true
    },
    {
      "word": "you",
      "start": 43.97999954223633,
      "end": 44.15999984741211,
      "aligned": true
    },
    {
      "word": "to",
      "start": 44.15999984741211,
      "end": 44.36000061035156,
      "aligned": true
    },
    {
      "word": "human",
      "start": 44.36000061035156,
      "end": 44.599998474121094,
      "aligned": true
    },
    {
      "word": "civilization.",
      "start": 44.599998474121094,
      "end": 45.08000183105469,
      "aligned": true
    },
    {
      "word": "Are",
      "start": 45.459999084472656,
      "end": 45.7400016784668,
      "aligned": true
    },
    {
      "word": "you",
      "start": 45.7400016784668,
      "end": 45.959999084472656,
      "aligned": true
    },
    {
      "word": "ready",
      "start": 45.959999084472656,
      "end": 46.060001373291016,
      "aligned": true
    },
    {
      "word": "to",
      "start": 46.060001373291016,
      "end": 46.540000915527344,
      "aligned": true
    },
    {
      "word": "depart?\"",
      "start": 46.540000915527344,
      "end": 46.540000915527344,
      "aligned": true
    },
    {
      "word": "Here",
      "start": 47.20000076293945,
      "end": 47.439998626708984,
      "aligned": true
    },
    {
      "word": "it",
      "start": 47.439998626708984,
      "end": 47.58000183105469,
      "aligned": true
    },
    {
      "word": "is—the",
      "start": 47.58000183105469,
      "end": 48.279998779296875,
      "aligned": false
    },
    {
      "word": "moment.",
      "start": 48.279998779296875,
      "end": 48.599998474121094,
      "aligned": true
    },
    {
      "word": "In",
      "start": 49.15999984741211,
      "end": 49.279998779296875,
      "aligned": true
    },
    {
      "word": "my",
      "start": 49.279998779296875,
      "end": 49.68000030517578,
      "aligned": true
    },
    {
      "word": "mind,",
      "start": 49.68000030517578,
      "end": 49.7400016784668,
      "aligned": true
    },
    {
      "word": "Buddy",
      "start": 49.7599983215332,
      "end": 49.959999084472656,
      "aligned": true
    },
    {
      "word": "says",
      "start": 49.959999084472656,
      "end": 50.2400016784668,
      "aligned": true
    },
    {
      "word": "quietly—«You've",
      "start": 50.2400016784668,
      "end": 51.5,
      "aligned": false
    },
    {
      "word": "got",
      "start": 51.5,
      "end": 51.68000030517578,
      "aligned": true
    },
    {
      "word": "this,",
      "start": 51.68000030517578,
      "end": 52,
      "aligned": true
    },
    {
      "word": "Kira.»",
      "start": 52.08000183105469,
      "end": 52.20000076293945,
      "aligned": true
    },
    {
      "word": "I",
      "start": 52.5,
      "end": 53.02000045776367,
      "aligned": true
    },
    {
      "word": "say,",
      "start": 53.02000045776367,
      "end": 53.2599983215332,
      "aligned": true
    },
    {
      "word": "\"Thanks,",
      "start": 53.34000015258789,
      "end": 53.540000915527344,
      "aligned": true
    },
    {
      "word": "Buddy.\"",
      "start": 53.599998474121094,
      "end": 53.7599983215332,
      "aligned": true
    },
    {
      "word": "This",
      "start": 54.060001373291016,
      "end": 54.34000015258789,
      "aligned": true
    },
    {
      "word": "is",
      "start": 54.34000015258789,
      "end": 54.5,
      "aligned": true
    },
    {
      "word": "the",
      "start": 54.5,
      "end": 54.79999923706055,
      "aligned": true
    },
    {
      "word": "scene",
      "start": 54.79999923706055,
      "end": 54.880001068115234,
      "aligned": true
    },
    {
      "word": "from",
      "start": 54.880001068115234,
      "end": 55.119998931884766,
      "aligned": true
    },
    {
      "word": "every",
      "start": 55.119998931884766,
      "end": 55.540000915527344,
      "aligned": true
    },
    {
      "word": "TV",
      "start": 55.540000915527344,
      "end": 55.900001525878906,
      "aligned": true
    },
    {
      "word": "finale—the",
      "start": 55.900001525878906,
      "end": 56.7599983215332,
      "aligned": false
    },
    {
      "word": "moment",
      "start": 56.7599983215332,
      "end": 57.060001373291016,
      "aligned": true
    },
    {
      "word": "the",
      "start": 57.060001373291016,
      "end": 57.619998931884766,
      "aligned": true
    },
    {
      "word": "hero",
      "start": 57.619998931884766,
      "end": 57.619998931884766,
      "aligned": true
    },
    {
      "word": "makes",
      "start": 57.619998931884766,
      "end": 57.880001068115234,
      "aligned": true
    },
    {
      "word": "their",
      "start": 57.880001068115234,
      "end": 58.119998931884766,
      "aligned": true
    },
    {
      "word": "big",
      "start": 58.119998931884766,
      "end": 58.47999954223633,
      "aligned": true
    },
    {
      "word": "choice.",
      "start": 58.47999954223633,
      "end": 58.86000061035156,
      "aligned": true
    },
    {
      "word": "In",
      "start": 59.459999084472656,
      "end": 59.459999084472656,
      "aligned": true
    },
    {
      "word": "Uncharted,",
      "start": 59.459999084472656,
      "end": 59.91999816894531,
      "aligned": true
    },
    {
      "word": "Mav",
      "start": 60.560001373291016,
      "end": 60.560001373291016,
      "aligned": true
    },
    {
      "word": "would",
      "start": 60.560001373291016,
      "end": 60.720001220703125,
      "aligned": true
    },
    {
      "word": "have",
      "start": 60.720001220703125,
      "end": 60.880001068115234,
      "aligned": true
    },
    {
      "word": "a",
      "start": 60.880001068115234,
      "end": 61.099998474121094,
      "aligned": true
    },
    {
      "word": "prepared,",
      "start": 61.099998474121094,
      "end": 61.400001525878906,
      "aligned": true
    },
    {
      "word": "dramatic",
      "start": 63.02000045776367,
      "end": 63.2400016784668,
      "aligned": true
    },
    {
      "word": "speech—dramatic",
      "start": 63.2400016784668,
      "end": 63.2400016784668,
      "aligned": false
    },
    {
      "word": "lighting,",
      "start": 63.2400016784668,
      "end": 63.65999984741211,
      "aligned": true
    },
    {
      "word": "swelling",
      "start": 64.45999908447266,
      "end": 64.45999908447266,
      "aligned": true
    },
    {
      "word": "music.",
      "start": 64.45999908447266,
      "end": 64.94000244140625,
      "aligned": true
    },
    {
      "word": "I",
      "start": 65.41999816894531,
      "end": 65.44000244140625,
      "aligned": true
    },
    {
      "word": "don't",
      "start": 65.44000244140625,
      "end": 65.63999938964844,
      "aligned": true
    },
    {
      "word": "need",
      "start": 65.63999938964844,
      "end": 65.81999969482422,
      "aligned": true
    },
    {
      "word": "that.",
      "start": 65.81999969482422,
      "end": 66.12000274658203,
      "aligned": true
    },
    {
      "word": "I",
      "start": 66.44000244140625,
      "end": 66.55999755859375,
      "aligned": true
    },
    {
      "word": "just",
      "start": 66.55999755859375,
      "end": 66.80000305175781,
      "aligned": true
    },
    {
      "word": "need",
      "start": 66.80000305175781,
      "end": 66.91999816894531,
      "aligned": true
    },
    {
      "word": "to",
      "start": 66.91999816894531,
      "end": 67.22000122070312,
      "aligned": true
    },
    {
      "word": "tell",
      "start": 67.22000122070312,
      "end": 67.22000122070312,
      "aligned": true
    },
    {
      "word": "the",
      "start": 67.22000122070312,
      "end": 67.73999786376953,
      "aligned": true
    },
    {
      "word": "truth.",
      "start": 67.73999786376953,
      "end": 67.73999786376953,
      "aligned": true
    },
    {
      "word": "I",
      "start": 68.19999694824219,
      "end": 68.23999786376953,
      "aligned": true
    },
    {
      "word": "say",
      "start": 68.23999786376953,
      "end": 68.5199966430664,
      "aligned": true
    },
    {
      "word": "clearly,",
      "start": 68.5199966430664,
      "end": 68.94000244140625,
      "aligned": true
    },
    {
      "word": "\"Thank",
      "start": 69.33999633789062,
      "end": 69.54000091552734,
      "aligned": true
    },
    {
      "word": "you",
      "start": 69.54000091552734,
      "end": 69.66000366210938,
      "aligned": true
    },
    {
      "word": "for",
      "start": 69.66000366210938,
      "end": 69.94000244140625,
      "aligned": true
    },
    {
      "word": "coming.",
      "start": 69.94000244140625,
      "end": 70.12000274658203,
      "aligned": true
    },
    {
      "word": "But",
      "start": 70.5,
      "end": 70.62000274658203,
      "aligned": true
    },
    {
      "word": "I'm",
      "start": 70.62000274658203,
      "end": 70.95999908447266,
      "aligned": true
    },
    {
      "word": "choosing",
      "start": 70.95999908447266,
      "end": 71.18000030517578,
      "aligned": true
    },
    {
      "word": "to",
      "start": 71.18000030517578,
      "end": 71.54000091552734,
      "aligned": true
    },
    {
      "word": "stay",
      "start": 71.54000091552734,
      "end": 71.63999938964844,
      "aligned": true
    },
    {
      "word": "here.",
      "start": 71.63999938964844,
      "end": 71.91999816894531,
      "aligned": true
    },
    {
      "word": "This",
      "start": 72.23999786376953,
      "end": 72.44000244140625,
      "aligned": true
    },
    {
      "word": "is",
      "start": 72.44000244140625,
      "end": 72.5999984741211,
      "aligned": true
    },
    {
      "word": "my",
      "start": 72.5999984741211,
      "end": 72.81999969482422,
      "aligned": true
    },
    {
      "word": "home.\"",
      "start": 72.81999969482422,
      "end": 73.05999755859375,
      "aligned": true
    },
    {
      "word": "Captain",
      "start": 73.69999694824219,
      "end": 73.95999908447266,
      "aligned": true
    },
    {
      "word": "Torres",
      "start": 73.95999908447266,
      "end": 74.31999969482422,
      "aligned": true
    },
    {
      "word": "blinks.",
      "start": 74.31999969482422,
      "end": 74.63999938964844,
      "aligned": true
    },
    {
      "word": "He",
      "start": 75.0999984741211,
      "end": 75.23999786376953,
      "aligned": true
    },
    {
      "word": "says,",
      "start": 75.23999786376953,
      "end": 75.5,
      "aligned": true
    },
    {
      "word": "\"I'm",
      "start": 75.83999633789062,
      "end": 76.27999877929688,
      "aligned": true
    },
    {
      "word": "sorry—what?\"",
      "start": 76.27999877929688,
      "end": 77.41999816894531,
      "aligned": false
    },
    {
      "word": "I",
      "start": 77.41999816894531,
      "end": 77.91999816894531,
      "aligned": true
    },
    {
      "word": "say,",
      "start": 77.91999816894531,
      "end": 78.18000030517578,
      "aligned": true
    },
    {
      "word": "\"I'm",
      "start": 78.23999786376953,
      "end": 78.76000213623047,
      "aligned": true
    },
    {
      "word": "choosing",
      "start": 78.76000213623047,
      "end": 78.76000213623047,
      "aligned": true
    },
    {
      "word": "to",
      "start": 78.76000213623047,
      "end": 79.23999786376953,
      "aligned": true
    },
    {
      "word": "remain",
      "start": 79.23999786376953,
      "end": 79.23999786376953,
      "aligned": true
    },
    {
      "word": "with",
      "start": 79.23999786376953,
      "end": 79.41999816894531,
      "aligned": true
    },
    {
      "word": "this",
      "start": 79.41999816894531,
      "end": 79.69999694824219,
      "aligned": true
    },
    {
      "word": "community.",
      "start": 79.69999694824219,
      "end": 80.0199966430664,
      "aligned": true
    },
    {
      "word": "I'm",
      "start": 80.22000122070312,
      "end": 80.62000274658203,
      "aligned": true
    },
    {
      "word": "not",
      "start": 80.62000274658203,
      "end": 80.81999969482422,
      "aligned": true
    },
    {
      "word": "being",
      "start": 80.81999969482422,
      "end": 81.05999755859375,
      "aligned": true
    },
    {
      "word": "held—this",
      "start": 81.05999755859375,
      "end": 81.58000183105469,
      "aligned": false
    },
    {
      "word": "is",
      "start": 81.58000183105469,
      "end": 81.77999877929688,
      "aligned": true
    },
    {
      "word": "my",
      "start": 81.77999877929688,
      "end": 82.0199966430664,
      "aligned": true
    },
    {
      "word": "free",
      "start": 82.0199966430664,
      "end": 82.22000122070312,
      "aligned": true
    },
    {
      "word": "decision.\"",
      "start": 82.22000122070312,
      "end": 82.55999755859375,
      "aligned": true
    },
    {
      "word": "The",
      "start": 82.9000015258789,
      "end": 83.22000122070312,
      "aligned": true
    },
    {
      "word": "medical",
      "start": 83.22000122070312,
      "end": 83.55999755859375,
      "aligned": true
    },
    {
      "word": "officer—Dr.",
      "start": 83.55999755859375,
      "end": 84.83999633789062,
      "aligned": false
    },
    {
      "word": "Chen,",
      "start": 84.83999633789062,
      "end": 84.83999633789062,
      "aligned": true
    },
    {
      "word": "according",
      "start": 85.16000366210938,
      "end": 85.41999816894531,
      "aligned": true
    },
    {
      "word": "to",
      "start": 85.41999816894531,
      "end": 85.58000183105469,
      "aligned": true
    },
    {
      "word": "her",
      "start": 85.58000183105469,
      "end": 85.87999725341797,
      "aligned": true
    },
    {
      "word": "badge—steps",
      "start": 85.87999725341797,
      "end": 86.72000122070312,
      "aligned": false
    },
    {
      "word": "forward",
      "start": 86.72000122070312,
      "end": 87.22000122070312,
      "aligned": true
    },
    {
      "word": "immediately.",
      "start": 87.22000122070312,
      "end": 87.76000213623047,
      "aligned": true
    },
    {
      "word": "Dr.",
      "start": 88.26000213623047,
      "end": 88.4000015258789,
      "aligned": true
    },
    {
      "word": "Chen",
      "start": 88.62000274658203,
      "end": 88.62000274658203,
      "aligned": true
    },
    {
      "word": "says,",
      "start": 88.62000274658203,
      "end": 89.0199966430664,
      "aligned": true
    },
    {
      "word": "\"We",
      "start": 89.41999816894531,
      "end": 89.44000244140625,
      "aligned": true
    },
    {
      "word": "need",
      "start": 89.44000244140625,
      "end": 89.68000030517578,
      "aligned": true
    },
    {
      "word": "to",
      "start": 89.68000030517578,
      "end": 90.0999984741211,
      "aligned": true
    },
    {
      "word": "evaluate",
      "start": 90.0999984741211,
      "end": 90.23999786376953,
      "aligned": true
    },
    {
      "word": "you.",
      "start": 90.23999786376953,
      "end": 90.62000274658203,
      "aligned": true
    },
    {
      "word": "After",
      "start": 91,
      "end": 91.0999984741211,
      "aligned": true
    },
    {
      "word": "weeks",
      "start": 91.0999984741211,
      "end": 91.44000244140625,
      "aligned": true
    },
    {
      "word": "stranded,",
      "start": 91.44000244140625,
      "end": 91.80000305175781,
      "aligned": true
    },
    {
      "word": "there",
      "start": 92.62000274658203,
      "end": 92.72000122070312,
      "aligned": true
    },
    {
      "word": "could",
      "start": 92.72000122070312,
      "end": 92.91999816894531,
      "aligned": true
    },
    {
      "word": "be",
      "start": 92.91999816894531,
      "end": 93.26000213623047,
      "aligned": true
    },
    {
      "word": "psychological",
      "start": 93.26000213623047,
      "end": 93.69999694824219,
      "aligned": true
    },
    {
      "word": "effects—Stockholm",
      "start": 93.69999694824219,
      "end": 94.9800033569336,
      "aligned": false
    },
    {
      "word": "syndrome,",
      "start": 94.9800033569336,
      "end": 95.31999969482422,
      "aligned": true
    },
    {
      "word": "alien",
      "start": 95.86000061035156,
      "end": 96.0199966430664,
      "aligned": true
    },
    {
      "word": "influence…\"",
      "start": 96.0199966430664,
      "end": 96.54000091552734,
      "aligned": true
    },
    {
      "word": "I",
      "start": 96.72000122070312,
      "end": 97.19999694824219,
      "aligned": true
    },
    {
      "word": "say,",
      "start": 97.19999694824219,
      "end": 97.44000244140625,
      "aligned": true
    },
    {
      "word": "\"You're",
      "start": 97.80000305175781,
      "end": 98.0199966430664,
      "aligned": true
    },
    {
      "word": "welcome",
      "start": 98.0199966430664,
      "end": 98.26000213623047,
      "aligned": true
    },
    {
      "word": "to",
      "start": 98.26000213623047,
      "end": 98.55999755859375,
      "aligned": true
    },
    {
      "word": "scan",
      "start": 98.55999755859375,
      "end": 98.69999694824219,
      "aligned": true
    },
    {
      "word": "me—I'm",
      "start": 98.69999694824219,
      "end": 99.58000183105469,
      "aligned": false
    },
    {
      "word": "neurologically",
      "start": 99.58000183105469,
      "end": 100.0199966430664,
      "aligned": true
    },
    {
      "word": "sound,",
      "start": 100.0199966430664,
      "end": 100.45999908447266,
      "aligned": true
    },
    {
      "word": "fully",
      "start": 100.9000015258789,
      "end": 101.12000274658203,
      "aligned": true
    },
    {
      "word": "lucid,",
      "start": 101.12000274658203,
      "end": 101.5199966430664,
      "aligned": true
    },
    {
      "word": "and",
      "start": 101.66000366210938,
      "end": 101.80000305175781,
      "aligned": true
    },
    {
      "word": "making",
      "start": 101.80000305175781,
      "end": 102,
      "aligned": true
    },
    {
      "word": "this",
      "start": 102,
      "end": 102.36000061035156,
      "aligned": true
    },
    {
      "word": "choice",
      "start": 102.36000061035156,
      "end": 102.62000274658203,
      "aligned": true
    },
    {
      "word": "freely.\"",
      "start": 102.62000274658203,
      "end": 103,
      "aligned": true
    },
    {
      "word": "Dr.",
      "start": 103.4800033569336,
      "end": 104,
      "aligned": true
    },
    {
      "word": "Chen",
      "start": 104.22000122070312,
      "end": 104.23999786376953,
      "aligned": true
    },
    {
      "word": "pulls",
      "start": 104.23999786376953,
      "end": 104.62000274658203,
      "aligned": true
    },
    {
      "word": "out",
      "start": 104.62000274658203,
      "end": 104.87999725341797,
      "aligned": true
    },
    {
      "word": "a",
      "start": 104.87999725341797,
      "end": 105.36000061035156,
      "aligned": true
    },
    {
      "word": "medical",
      "start": 105.36000061035156,
      "end": 105.36000061035156,
      "aligned": true
    },
    {
      "word": "scanner",
      "start": 105.36000061035156,
      "end": 105.66000366210938,
      "aligned": true
    },
    {
      "word": "and",
      "start": 105.66000366210938,
      "end": 106.04000091552734,
      "aligned": true
    },
    {
      "word": "runs",
      "start": 106.04000091552734,
      "end": 106.19999694824219,
      "aligned": true
    },
    {
      "word": "it",
      "start": 106.19999694824219,
      "end": 106.44000244140625,
      "aligned": true
    },
    {
      "word": "over",
      "start": 106.44000244140625,
      "end": 106.54000091552734,
      "aligned": true
    },
    {
      "word": "me—she",
      "start": 106.54000091552734,
      "end": 107.41999816894531,
      "aligned": false
    },
    {
      "word": "frowns",
      "start": 107.41999816894531,
      "end": 107.73999786376953,
      "aligned": true
    },
    {
      "word": "at",
      "start": 107.73999786376953,
      "end": 107.87999725341797,
      "aligned": true
    },
    {
      "word": "the",
      "start": 107.87999725341797,
      "end": 108.04000091552734,
      "aligned": true
    },
    {
      "word": "readings.",
      "start": 108.04000091552734,
      "end": 108.30000305175781,
      "aligned": true
    },
    {
      "word": "Dr.",
      "start": 108.30000305175781,
      "end": 108.9800033569336,
      "aligned": true
    },
    {
      "word": "Chen",
      "start": 109.23999786376953,
      "end": 109.27999877929688,
      "aligned": true
    },
    {
      "word": "says,",
      "start": 109.27999877929688,
      "end": 109.69999694824219,
      "aligned": true
    },
    {
      "word": "\"Vitals",
      "start": 110.26000213623047,
      "end": 110.37999725341797,
      "aligned": true
    },
    {
      "word": "normal.",
      "start": 110.37999725341797,
      "end": 110.76000213623047,
      "aligned": true
    },
    {
      "word": "No",
      "start": 110.87999725341797,
      "end": 111.4800033569336,
      "aligned": true
    },
    {
      "word": "foreign",
      "start": 111.4800033569336,
      "end": 111.76000213623047,
      "aligned": true
    },
    {
      "word": "substances.",
      "start": 111.76000213623047,
      "end": 112.31999969482422,
      "aligned": true
    },
    {
      "word": "Neural",
      "start": 112.9800033569336,
      "end": 113.05999755859375,
      "aligned": true
    },
    {
      "word": "patterns",
      "start": 113.05999755859375,
      "end": 113.4000015258789,
      "aligned": true
    },
    {
      "word": "indicate…",
      "start": 113.4000015258789,
      "end": 113.91999816894531,
      "aligned": true
    },
    {
      "word": "you're",
      "start": 113.91999816894531,
      "end": 114.36000061035156,
      "aligned": true
    },
    {
      "word": "actually",
      "start": 114.36000061035156,
      "end": 114.94000244140625,
      "aligned": true
    },
    {
      "word": "healthier",
      "start": 114.94000244140625,
      "end": 115.27999877929688,
      "aligned": true
    },
    {
      "word": "than",
      "start": 115.27999877929688,
      "end": 115.5,
      "aligned": true
    },
    {
      "word": "baseline.\"",
      "start": 115.5,
      "end": 115.95999908447266,
      "aligned": true
    },
    {
      "word": "I",
      "start": 116.5,
      "end": 116.63999938964844,
      "aligned": true
    },
    {
      "word": "say,",
      "start": 116.63999938964844,
      "end": 116.9000015258789,
      "aligned": true
    },
    {
      "word": "\"I",
      "start": 117.16000366210938,
      "end": 117.27999877929688,
      "aligned": true
    },
    {
      "word": "told",
      "start": 117.27999877929688,
      "end": 117.5199966430664,
      "aligned": true
    },
    {
      "word": "you.\"",
      "start": 117.5199966430664,
      "end": 117.86000061035156,
      "aligned": true
    },
    {
      "word": "Captain",
      "start": 118.44000244140625,
      "end": 118.62000274658203,
      "aligned": true
    },
    {
      "word": "Torres",
      "start": 118.62000274658203,
      "end": 118.91999816894531,
      "aligned": true
    },
    {
      "word": "is",
      "start": 118.91999816894531,
      "end": 119.22000122070312,
      "aligned": true
    },
    {
      "word": "processing",
      "start": 119.22000122070312,
      "end": 119.58000183105469,
      "aligned": true
    },
    {
      "word": "this.",
      "start": 119.58000183105469,
      "end": 120.04000091552734,
      "aligned": true
    },
    {
      "word": "He",
      "start": 120.4000015258789,
      "end": 120.5199966430664,
      "aligned": true
    },
    {
      "word": "says,",
      "start": 120.5199966430664,
      "end": 120.80000305175781,
      "aligned": true
    },
    {
      "word": "\"Ms.",
      "start": 121.27999877929688,
      "end": 121.4800033569336,
      "aligned": true
    },
    {
      "word": "Voss,",
      "start": 121.5199966430664,
      "end": 121.76000213623047,
      "aligned": true
    },
    {
      "word": "you've",
      "start": 122.18000030517578,
      "end": 122.41999816894531,
      "aligned": true
    },
    {
      "word": "been",
      "start": 122.41999816894531,
      "end": 122.77999877929688,
      "aligned": true
    },
    {
      "word": "stranded",
      "start": 122.77999877929688,
      "end": 122.81999969482422,
      "aligned": true
    },
    {
      "word": "with",
      "start": 122.81999969482422,
      "end": 123.22000122070312,
      "aligned": true
    },
    {
      "word": "alien",
      "start": 123.22000122070312,
      "end": 123.44000244140625,
      "aligned": true
    },
    {
      "word": "life",
      "start": 123.44000244140625,
      "end": 123.80000305175781,
      "aligned": true
    },
    {
      "word": "forms",
      "start": 123.80000305175781,
      "end": 123.9800033569336,
      "aligned": true
    },
    {
      "word": "for",
      "start": 123.9800033569336,
      "end": 124.58000183105469,
      "aligned": true
    },
    {
      "word": "weeks.",
      "start": 124.58000183105469,
      "end": 124.58000183105469,
      "aligned": true
    },
    {
      "word": "It's",
      "start": 124.9000015258789,
      "end": 125.22000122070312,
      "aligned": true
    },
    {
      "word": "natural",
      "start": 125.22000122070312,
      "end": 125.5199966430664,
      "aligned": true
    },
    {
      "word": "to",
      "start": 125.5199966430664,
      "end": 125.9800033569336,
      "aligned": true
    },
    {
      "word": "form",
      "start": 125.9800033569336,
      "end": 125.9800033569336,
      "aligned": true
    },
    {
      "word": "attachment",
      "start": 125.9800033569336,
      "end": 126.37999725341797,
      "aligned": true
    },
    {
      "word": "to",
      "start": 126.37999725341797,
      "end": 126.62000274658203,
      "aligned": true
    },
    {
      "word": "your",
      "start": 126.62000274658203,
      "end": 126.91999816894531,
      "aligned": true
    },
    {
      "word": "rescuers,",
      "start": 126.91999816894531,
      "end": 127.30000305175781,
      "aligned": true
    },
    {
      "word": "but—\"",
      "start": 127.41999816894531,
      "end": 127.55999755859375,
      "aligned": true
    },
    {
      "word": "I",
      "start": 127.55999755859375,
      "end": 128.1199951171875,
      "aligned": true
    },
    {
      "word": "say,",
      "start": 128.1199951171875,
      "end": 128.44000244140625,
      "aligned": true
    },
    {
      "word": "\"They're",
      "start": 128.67999267578125,
      "end": 128.89999389648438,
      "aligned": true
    },
    {
      "word": "not",
      "start": 128.89999389648438,
      "end": 129.0800018310547,
      "aligned": true
    },
    {
      "word": "my",
      "start": 129.0800018310547,
      "end": 129.4600067138672,
      "aligned": true
    },
    {
      "word": "rescuers—they're",
      "start": 129.4600067138672,
      "end": 130.39999389648438,
      "aligned": false
    },
    {
      "word": "my",
      "start": 130.39999389648438,
      "end": 130.67999267578125,
      "aligned": true
    },
    {
      "word": "community.\"",
      "start": 130.67999267578125,
      "end": 131.02000427246094,
      "aligned": true
    },
    {
      "word": "Captain",
      "start": 131.75999450683594,
      "end": 131.9199981689453,
      "aligned": true
    },
    {
      "word": "Torres",
      "start": 131.9199981689453,
      "end": 132.24000549316406,
      "aligned": true
    },
    {
      "word": "says,",
      "start": 132.24000549316406,
      "end": 132.63999938964844,
      "aligned": true
    },
    {
      "word": "\"They're",
      "start": 133.02000427246094,
      "end": 133.1999969482422,
      "aligned": true
    },
    {
      "word": "plants.\"",
      "start": 133.1999969482422,
      "end": 133.5800018310547,
      "aligned": true
    },
    {
      "word": "I",
      "start": 134.10000610351562,
      "end": 134.32000732421875,
      "aligned": true
    },
    {
      "word": "say,",
      "start": 134.32000732421875,
      "end": 134.55999755859375,
      "aligned": true
    },
    {
      "word": "\"They're",
      "start": 134.60000610351562,
      "end": 135.10000610351562,
      "aligned": true
    },
    {
      "word": "people",
      "start": 135.10000610351562,
      "end": 135.4199981689453,
      "aligned": true
    },
    {
      "word": "who",
      "start": 135.4199981689453,
      "end": 135.75999450683594,
      "aligned": true
    },
    {
      "word": "value",
      "start": 135.75999450683594,
      "end": 136.02000427246094,
      "aligned": true
    },
    {
      "word": "my",
      "start": 136.02000427246094,
      "end": 136.5,
      "aligned": true
    },
    {
      "word": "individual",
      "start": 136.5,
      "end": 136.97999572753906,
      "aligned": true
    },
    {
      "word": "contribution—which",
      "start": 136.97999572753906,
      "end": 138.24000549316406,
      "aligned": false
    },
    {
      "word": "is",
      "start": 138.24000549316406,
      "end": 138.47999572753906,
      "aligned": true
    },
    {
      "word": "more",
      "start": 138.47999572753906,
      "end": 138.67999267578125,
      "aligned": true
    },
    {
      "word": "than",
      "start": 138.67999267578125,
      "end": 138.77999877929688,
      "aligned": true
    },
    {
      "word": "I",
      "start": 138.77999877929688,
      "end": 138.9600067138672,
      "aligned": true
    },
    {
      "word": "can",
      "start": 138.9600067138672,
      "end": 139.17999267578125,
      "aligned": true
    },
    {
      "word": "say",
      "start": 139.17999267578125,
      "end": 139.36000061035156,
      "aligned": true
    },
    {
      "word": "for",
      "start": 139.36000061035156,
      "end": 139.63999938964844,
      "aligned": true
    },
    {
      "word": "the",
      "start": 139.63999938964844,
      "end": 139.83999633789062,
      "aligned": true
    },
    {
      "word": "human",
      "start": 139.83999633789062,
      "end": 140.1199951171875,
      "aligned": true
    },
    {
      "word": "bureaucracy",
      "start": 140.1199951171875,
      "end": 140.60000610351562,
      "aligned": true
    },
    {
      "word": "that",
      "start": 140.60000610351562,
      "end": 141.1999969482422,
      "aligned": true
    },
    {
      "word": "sent",
      "start": 141.1999969482422,
      "end": 141.39999389648438,
      "aligned": true
    },
    {
      "word": "me",
      "start": 141.39999389648438,
      "end": 141.60000610351562,
      "aligned": true
    },
    {
      "word": "on",
      "start": 141.60000610351562,
      "end": 141.77999877929688,
      "aligned": true
    },
    {
      "word": "that",
      "start": 141.77999877929688,
      "end": 141.97999572753906,
      "aligned": true
    },
    {
      "word": "courier",
      "start": 141.97999572753906,
      "end": 142.3000030517578,
      "aligned": false
    },
    {
      "word": "mission.\"",
      "start": 142.3000030517578,
      "end": 142.60000610351562,
      "aligned": true
    },
    {
      "word": "Captain",
      "start": 143.55999755859375,
      "end": 143.55999755859375,
      "aligned": true
    },
    {
      "word": "Torres",
      "start": 143.55999755859375,
      "end": 143.8800048828125,
      "aligned": true
    },
    {
      "word": "looks",
      "start": 143.8800048828125,
      "end": 144.16000366210938,
      "aligned": true
    },
    {
      "word": "past",
      "start": 144.16000366210938,
      "end": 144.5399932861328,
      "aligned": true
    },
    {
      "word": "me",
      "start": 144.5399932861328,
      "end": 144.74000549316406,
      "aligned": true
    },
    {
      "word": "at",
      "start": 144.74000549316406,
      "end": 144.86000061035156,
      "aligned": true
    },
    {
      "word": "the",
      "start": 145.8800048828125,
      "end": 146.0399932861328,
      "aligned": true
    },
    {
      "word": "facility—the",
      "start": 146.0399932861328,
      "end": 146.0399932861328,
      "aligned": false
    },
    {
      "word": "weird,",
      "start": 146.0399932861328,
      "end": 146.3800048828125,
      "aligned": true
    },
    {
      "word": "wonderful",
      "start": 147,
      "end": 147,
      "aligned": true
    },
    {
      "word": "plant",
      "start": 147,
      "end": 147.32000732421875,
      "aligned": true
    },
    {
      "word": "construction,",
      "start": 147.32000732421875,
      "end": 147.8000030517578,
      "aligned": true
    },
    {
      "word": "the",
      "start": 148.24000549316406,
      "end": 148.4199981689453,
      "aligned": true
    },
    {
      "word": "artistic",
      "start": 148.4199981689453,
      "end": 148.75999450683594,
      "aligned": true
    },
    {
      "word": "growth,",
      "start": 148.75999450683594,
      "end": 149.1999969482422,
      "aligned": true
    },
    {
      "word": "the",
      "start": 149.3000030517578,
      "end": 150.17999267578125,
      "aligned": true
    },
    {
      "word": "absurd",
      "start": 150.17999267578125,
      "end": 150.47999572753906,
      "aligned": true
    },
    {
      "word": "but",
      "start": 150.47999572753906,
      "end": 150.94000244140625,
      "aligned": true
    },
    {
      "word": "functional",
      "start": 150.94000244140625,
      "end": 151.13999938964844,
      "aligned": true
    },
    {
      "word": "design.",
      "start": 151.13999938964844,
      "end": 151.66000366210938,
      "aligned": true
    },
    {
      "word": "He",
      "start": 151.9600067138672,
      "end": 152.13999938964844,
      "aligned": true
    },
    {
      "word": "says,",
      "start": 152.13999938964844,
      "end": 152.4199981689453,
      "aligned": true
    },
    {
      "word": "\"This",
      "start": 152.77999877929688,
      "end": 152.94000244140625,
      "aligned": true
    },
    {
      "word": "isn't",
      "start": 152.94000244140625,
      "end": 153.1999969482422,
      "aligned": true
    },
    {
      "word": "an",
      "start": 153.1999969482422,
      "end": 153.83999633789062,
      "aligned": true
    },
    {
      "word": "appropriate",
      "start": 153.83999633789062,
      "end": 153.83999633789062,
      "aligned": true
    },
    {
      "word": "environment",
      "start": 153.83999633789062,
      "end": 154.24000549316406,
      "aligned": true
    },
    {
      "word": "for",
      "start": 154.24000549316406,
      "end": 154.5399932861328,
      "aligned": true
    },
    {
      "word": "a",
      "start": 154.5399932861328,
      "end": 154.9199981689453,
      "aligned": true
    },
    {
      "word": "human.\"",
      "start": 154.9199981689453,
      "end": 154.9199981689453,
      "aligned": true
    },
    {
      "word": "I",
      "start": 155.39999389648438,
      "end": 155.6199951171875,
      "aligned": true
    },
    {
      "word": "say",
      "start": 155.6199951171875,
      "end": 155.8800048828125,
      "aligned": true
    },
    {
      "word": "calmly,",
      "start": 155.8800048828125,
      "end": 156.22000122070312,
      "aligned": true
    },
    {
      "word": "\"It's",
      "start": 156.32000732421875,
      "end": 156.82000732421875,
      "aligned": true
    },
    {
      "word": "more",
      "start": 156.82000732421875,
      "end": 157.0399932861328,
      "aligned": true
    },
    {
      "word": "appropriate",
      "start": 157.0399932861328,
      "end": 157.33999633789062,
      "aligned": true
    },
    {
      "word": "than",
      "start": 157.33999633789062,
      "end": 157.66000366210938,
      "aligned": true
    },
    {
      "word": "any",
      "start": 157.66000366210938,
      "end": 158.0399932861328,
      "aligned": true
    },
    {
      "word": "environment",
      "start": 158.0399932861328,
      "end": 158.3000030517578,
      "aligned": true
    },
    {
      "word": "I've",
      "start": 158.3000030517578,
      "end": 158.86000061035156,
      "aligned": true
    },
    {
      "word": "lived",
      "start": 158.86000061035156,
      "end": 158.86000061035156,
      "aligned": true
    },
    {
      "word": "in.",
      "start": 158.86000061035156,
      "end": 159.5,
      "aligned": true
    },
    {
      "word": "Captain,",
      "start": 159.72000122070312,
      "end": 159.83999633789062,
      "aligned": true
    },
    {
      "word": "I",
      "start": 159.97999572753906,
      "end": 160.60000610351562,
      "aligned": true
    },
    {
      "word": "understand",
      "start": 160.60000610351562,
      "end": 160.89999389648438,
      "aligned": true
    },
    {
      "word": "this",
      "start": 160.89999389648438,
      "end": 161.24000549316406,
      "aligned": true
    },
    {
      "word": "is",
      "start": 161.24000549316406,
      "end": 161.5,
      "aligned": true
    },
    {
      "word": "irregular—but",
      "start": 161.5,
      "end": 162.27999877929688,
      "aligned": false
    },
    {
      "word": "I'm",
      "start": 162.27999877929688,
      "end": 162.5399932861328,
      "aligned": true
    },
    {
      "word": "a",
      "start": 162.5399932861328,
      "end": 162.9199981689453,
      "aligned": true
    },
    {
      "word": "legal",
      "start": 162.9199981689453,
      "end": 162.9199981689453,
      "aligned": true
    },
    {
      "word": "adult,",
      "start": 162.9199981689453,
      "end": 163.25999450683594,
      "aligned": true
    },
    {
      "word": "sound",
      "start": 163.75999450683594,
      "end": 163.9600067138672,
      "aligned": true
    },
    {
      "word": "mind,",
      "start": 163.9600067138672,
      "end": 164.27999877929688,
      "aligned": true
    },
    {
      "word": "making",
      "start": 164.5800018310547,
      "end": 164.8800048828125,
      "aligned": true
    },
    {
      "word": "an",
      "start": 164.8800048828125,
      "end": 165.16000366210938,
      "aligned": true
    },
    {
      "word": "informed",
      "start": 165.16000366210938,
      "end": 165.4199981689453,
      "aligned": true
    },
    {
      "word": "choice.",
      "start": 165.4199981689453,
      "end": 165.83999633789062,
      "aligned": true
    },
    {
      "word": "I'm",
      "start": 166.0399932861328,
      "end": 166.63999938964844,
      "aligned": true
    },
    {
      "word": "choosing",
      "start": 166.63999938964844,
      "end": 166.63999938964844,
      "aligned": true
    },
    {
      "word": "to",
      "start": 166.63999938964844,
      "end": 167.17999267578125,
      "aligned": true
    },
    {
      "word": "stay.\"",
      "start": 167.17999267578125,
      "end": 167.17999267578125,
      "aligned": true
    },
    {
      "word": "Captain",
      "start": 167.17999267578125,
      "end": 168.02000427246094,
      "aligned": true
    },
    {
      "word": "Torres",
      "start": 168.02000427246094,
      "end": 168.3000030517578,
      "aligned": true
    },
    {
      "word": "says,",
      "start": 168.3000030517578,
      "end": 168.72000122070312,
      "aligned": true
    },
    {
      "word": "\"We",
      "start": 169.13999938964844,
      "end": 169.13999938964844,
      "aligned": true
    },
    {
      "word": "have",
      "start": 169.13999938964844,
      "end": 169.3800048828125,
      "aligned": true
    },
    {
      "word": "regulations—\"",
      "start": 169.3800048828125,
      "end": 170.0399932861328,
      "aligned": true
    },
    {
      "word": "I",
      "start": 170.5,
      "end": 170.63999938964844,
      "aligned": true
    },
    {
      "word": "say,",
      "start": 170.63999938964844,
      "end": 170.8800048828125,
      "aligned": true
    },
    {
      "word": "\"About",
      "start": 171.3000030517578,
      "end": 171.52000427246094,
      "aligned": true
    },
    {
      "word": "rescue",
      "start": 171.52000427246094,
      "end": 171.8800048828125,
      "aligned": true
    },
    {
      "word": "refusal?",
      "start": 171.8800048828125,
      "end": 172.27999877929688,
      "aligned": true
    },
    {
      "word": "Yes—I'm",
      "start": 172.27999877929688,
      "end": 173.6999969482422,
      "aligned": false
    },
    {
      "word": "refusing",
      "start": 173.6999969482422,
      "end": 174,
      "aligned": true
    },
    {
      "word": "rescue.",
      "start": 174,
      "end": 174.44000244140625,
      "aligned": true
    },
    {
      "word": "Not",
      "start": 174.75999450683594,
      "end": 175.0800018310547,
      "aligned": true
    },
    {
      "word": "because",
      "start": 175.0800018310547,
      "end": 175.33999633789062,
      "aligned": true
    },
    {
      "word": "I'm",
      "start": 175.33999633789062,
      "end": 175.86000061035156,
      "aligned": true
    },
    {
      "word": "impaired",
      "start": 175.86000061035156,
      "end": 175.86000061035156,
      "aligned": true
    },
    {
      "word": "or",
      "start": 175.86000061035156,
      "end": 176.24000549316406,
      "aligned": true
    },
    {
      "word": "coerced—because",
      "start": 176.24000549316406,
      "end": 177.16000366210938,
      "aligned": false
    },
    {
      "word": "I",
      "start": 177.16000366210938,
      "end": 177.5399932861328,
      "aligned": true
    },
    {
      "word": "found",
      "start": 177.5399932861328,
      "end": 177.60000610351562,
      "aligned": true
    },
    {
      "word": "something",
      "start": 177.60000610351562,
      "end": 178,
      "aligned": true
    },
    {
      "word": "rare:",
      "start": 178,
      "end": 178.27999877929688,
      "aligned": true
    },
    {
      "word": "_authentic",
      "start": 179.1999969482422,
      "end": 179.1999969482422,
      "aligned": true
    },
    {
      "word": "belonging_.\"",
      "start": 179.1999969482422,
      "end": 179.67999267578125,
      "aligned": true
    },
    {
      "word": "Dr.",
      "start": 179.8800048828125,
      "end": 180.1999969482422,
      "aligned": true
    },
    {
      "word": "Chen",
      "start": 180.3000030517578,
      "end": 180.4199981689453,
      "aligned": true
    },
    {
      "word": "continues",
      "start": 180.4199981689453,
      "end": 181.05999755859375,
      "aligned": true
    },
    {
      "word": "scanning.",
      "start": 181.05999755859375,
      "end": 181.52000427246094,
      "aligned": true
    },
    {
      "word": "Dr.",
      "start": 182.4600067138672,
      "end": 182.63999938964844,
      "aligned": true
    },
    {
      "word": "Chen",
      "start": 182.8000030517578,
      "end": 182.8800048828125,
      "aligned": true
    },
    {
      "word": "reports,",
      "start": 182.8800048828125,
      "end": 183.3800048828125,
      "aligned": true
    },
    {
      "word": "\"Her",
      "start": 184,
      "end": 184.02000427246094,
      "aligned": true
    },
    {
      "word": "well-being",
      "start": 184.02000427246094,
      "end": 184.4199981689453,
      "aligned": true
    },
    {
      "word": "indicators",
      "start": 184.4199981689453,
      "end": 184.9199981689453,
      "aligned": true
    },
    {
      "word": "are",
      "start": 184.9199981689453,
      "end": 185.3000030517578,
      "aligned": true
    },
    {
      "word": "significantly",
      "start": 185.3000030517578,
      "end": 185.86000061035156,
      "aligned": true
    },
    {
      "word": "elevated.",
      "start": 185.86000061035156,
      "end": 186.36000061035156,
      "aligned": true
    },
    {
      "word": "Stress",
      "start": 187.1199951171875,
      "end": 187.16000366210938,
      "aligned": true
    },
    {
      "word": "levels",
      "start": 187.16000366210938,
      "end": 187.4600067138672,
      "aligned": true
    },
    {
      "word": "below",
      "start": 187.4600067138672,
      "end": 187.8000030517578,
      "aligned": true
    },
    {
      "word": "norm,",
      "start": 187.8000030517578,
      "end": 188.13999938964844,
      "aligned": true
    },
    {
      "word": "social",
      "start": 188.72000122070312,
      "end": 188.86000061035156,
      "aligned": true
    },
    {
      "word": "integration",
      "start": 188.86000061035156,
      "end": 189.3000030517578,
      "aligned": true
    },
    {
      "word": "metrics",
      "start": 189.3000030517578,
      "end": 189.67999267578125,
      "aligned": true
    },
    {
      "word": "high,",
      "start": 189.67999267578125,
      "end": 190.0800018310547,
      "aligned": true
    },
    {
      "word": "psychological",
      "start": 190.6999969482422,
      "end": 191.02000427246094,
      "aligned": true
    },
    {
      "word": "markers",
      "start": 191.02000427246094,
      "end": 191.3800048828125,
      "aligned": true
    },
    {
      "word": "all",
      "start": 191.3800048828125,
      "end": 191.86000061035156,
      "aligned": true
    },
    {
      "word": "positive.\"",
      "start": 191.86000061035156,
      "end": 192.27999877929688,
      "aligned": true
    },
    {
      "word": "I",
      "start": 192.67999267578125,
      "end": 192.97999572753906,
      "aligned": true
    },
    {
      "word": "say,",
      "start": 192.97999572753906,
      "end": 193.25999450683594,
      "aligned": true
    },
    {
      "word": "\"That's",
      "start": 193.39999389648438,
      "end": 194.02000427246094,
      "aligned": true
    },
    {
      "word": "because",
      "start": 194.02000427246094,
      "end": 194.1999969482422,
      "aligned": true
    },
    {
      "word": "I'm",
      "start": 194.1999969482422,
      "end": 194.4199981689453,
      "aligned": true
    },
    {
      "word": "happy",
      "start": 194.4199981689453,
      "end": 194.6999969482422,
      "aligned": true
    },
    {
      "word": "here.\"",
      "start": 194.6999969482422,
      "end": 195.0399932861328,
      "aligned": true
    },
    {
      "word": "Captain",
      "start": 195.55999755859375,
      "end": 195.97999572753906,
      "aligned": true
    },
    {
      "word": "Torres",
      "start": 195.97999572753906,
      "end": 196.27999877929688,
      "aligned": true
    },
    {
      "word": "hesitates.",
      "start": 196.27999877929688,
      "end": 196.94000244140625,
      "aligned": true
    },
    {
      "word": "Captain",
      "start": 197.77999877929688,
      "end": 197.86000061035156,
      "aligned": true
    },
    {
      "word": "Torres",
      "start": 197.86000061035156,
      "end": 198.13999938964844,
      "aligned": true
    },
    {
      "word": "asks,",
      "start": 198.13999938964844,
      "end": 198.5800018310547,
      "aligned": true
    },
    {
      "word": "\"The",
      "start": 199.05999755859375,
      "end": 199.17999267578125,
      "aligned": true
    },
    {
      "word": "company",
      "start": 199.17999267578125,
      "end": 199.5399932861328,
      "aligned": true
    },
    {
      "word": "sent",
      "start": 199.5399932861328,
      "end": 199.8000030517578,
      "aligned": true
    },
    {
      "word": "us",
      "start": 199.8000030517578,
      "end": 199.9600067138672,
      "aligned": true
    },
    {
      "word": "to",
      "start": 199.9600067138672,
      "end": 200.4199981689453,
      "aligned": true
    },
    {
      "word": "extract",
      "start": 200.4199981689453,
      "end": 200.4199981689453,
      "aligned": true
    },
    {
      "word": "a",
      "start": 200.4199981689453,
      "end": 200.8800048828125,
      "aligned": true
    },
    {
      "word": "human",
      "start": 200.8800048828125,
      "end": 200.8800048828125,
      "aligned": true
    },
    {
      "word": "survivor.",
      "start": 200.8800048828125,
      "end": 201.3000030517578,
      "aligned": true
    },
    {
      "word": "Standard",
      "start": 202.0399932861328,
      "end": 202.1999969482422,
      "aligned": true
    },
    {
      "word": "protocol—\"",
      "start": 202.1999969482422,
      "end": 202.63999938964844,
      "aligned": true
    },
    {
      "word": "I",
      "start": 203.27999877929688,
      "end": 203.5,
      "aligned": true
    },
    {
      "word": "finish,",
      "start": 203.5,
      "end": 203.77999877929688,
      "aligned": true
    },
    {
      "word": "\"Doesn't",
      "start": 204.25999450683594,
      "end": 204.4199981689453,
      "aligned": true
    },
    {
      "word": "cover",
      "start": 204.4199981689453,
      "end": 204.63999938964844,
      "aligned": true
    },
    {
      "word": "this",
      "start": 204.63999938964844,
      "end": 204.8800048828125,
      "aligned": true
    },
    {
      "word": "situation.",
      "start": 204.8800048828125,
      "end": 205.36000061035156,
      "aligned": true
    },
    {
      "word": "I",
      "start": 205.97999572753906,
      "end": 206.13999938964844,
      "aligned": true
    },
    {
      "word": "know.",
      "start": 206.13999938964844,
      "end": 206.3800048828125,
      "aligned": true
    },
    {
      "word": "But",
      "start": 206.6999969482422,
      "end": 206.9199981689453,
      "aligned": true
    },
    {
      "word": "I'm",
      "start": 206.9199981689453,
      "end": 207.0800018310547,
      "aligned": true
    },
    {
      "word": "still",
      "start": 207.0800018310547,
      "end": 207.4199981689453,
      "aligned": true
    },
    {
      "word": "choosing",
      "start": 207.4199981689453,
      "end": 207.60000610351562,
      "aligned": true
    },
    {
      "word": "to",
      "start": 207.60000610351562,
      "end": 208.1999969482422,
      "aligned": true
    },
    {
      "word": "stay.\"",
      "start": 208.1999969482422,
      "end": 208.1999969482422,
      "aligned": true
    },
    {
      "word": "Holloway",
      "start": 209.17999267578125,
      "end": 209.22000122070312,
      "aligned": true
    },
    {
      "word": "approaches",
      "start": 209.22000122070312,
      "end": 209.67999267578125,
      "aligned": true
    },
    {
      "word": "carefully.",
      "start": 209.67999267578125,
      "end": 210.1999969482422,
      "aligned": true
    },
    {
      "word": "Holloway",
      "start": 210.94000244140625,
      "end": 211.10000610351562,
      "aligned": true
    },
    {
      "word": "says,",
      "start": 211.10000610351562,
      "end": 211.47999572753906,
      "aligned": true
    },
    {
      "word": "\"Captain",
      "start": 212.05999755859375,
      "end": 212.0800018310547,
      "aligned": true
    },
    {
      "word": "Torres,",
      "start": 212.0800018310547,
      "end": 212.4600067138672,
      "aligned": true
    },
    {
      "word": "I'm",
      "start": 212.6999969482422,
      "end": 213,
      "aligned": true
    },
    {
      "word": "the",
      "start": 213,
      "end": 213.25999450683594,
      "aligned": true
    },
    {
      "word": "facility",
      "start": 213.25999450683594,
      "end": 213.52000427246094,
      "aligned": true
    },
    {
      "word": "coordinator.",
      "start": 213.52000427246094,
      "end": 214.05999755859375,
      "aligned": true
    },
    {
      "word": "Kira",
      "start": 214.89999389648438,
      "end": 214.89999389648438,
      "aligned": true
    },
    {
      "word": "is",
      "start": 214.89999389648438,
      "end": 215.17999267578125,
      "aligned": true
    },
    {
      "word": "a",
      "start": 215.17999267578125,
      "end": 215.5399932861328,
      "aligned": true
    },
    {
      "word": "valued",
      "start": 215.5399932861328,
      "end": 215.72000122070312,
      "aligned": true
    },
    {
      "word": "community",
      "start": 215.72000122070312,
      "end": 216.1999969482422,
      "aligned": true
    },
    {
      "word": "member.",
      "start": 216.1999969482422,
      "end": 216.52000427246094,
      "aligned": true
    },
    {
      "word": "She's",
      "start": 216.97999572753906,
      "end": 217.33999633789062,
      "aligned": true
    },
    {
      "word": "free",
      "start": 217.33999633789062,
      "end": 217.4199981689453,
      "aligned": true
    },
    {
      "word": "to",
      "start": 217.4199981689453,
      "end": 217.86000061035156,
      "aligned": true
    },
    {
      "word": "leave",
      "start": 217.86000061035156,
      "end": 217.86000061035156,
      "aligned": true
    },
    {
      "word": "anytime",
      "start": 217.86000061035156,
      "end": 218.4600067138672,
      "aligned": true
    },
    {
      "word": "she",
      "start": 218.4600067138672,
      "end": 218.6999969482422,
      "aligned": true
    },
    {
      "word": "chooses.",
      "start": 218.6999969482422,
      "end": 219.0800018310547,
      "aligned": true
    },
    {
      "word": "We",
      "start": 219.52000427246094,
      "end": 219.67999267578125,
      "aligned": true
    },
    {
      "word": "would",
      "start": 219.67999267578125,
      "end": 219.9199981689453,
      "aligned": true
    },
    {
      "word": "never",
      "start": 219.9199981689453,
      "end": 220.17999267578125,
      "aligned": true
    },
    {
      "word": "hold",
      "start": 220.17999267578125,
      "end": 220.39999389648438,
      "aligned": true
    },
    {
      "word": "her",
      "start": 220.39999389648438,
      "end": 220.6199951171875,
      "aligned": true
    },
    {
      "word": "against",
      "start": 220.6199951171875,
      "end": 220.83999633789062,
      "aligned": true
    },
    {
      "word": "her",
      "start": 220.83999633789062,
      "end": 221.05999755859375,
      "aligned": true
    },
    {
      "word": "will.\"",
      "start": 221.05999755859375,
      "end": 221.27999877929688,
      "aligned": true
    },
    {
      "word": "Captain",
      "start": 221.9199981689453,
      "end": 222.33999633789062,
      "aligned": true
    },
    {
      "word": "Torres",
      "start": 222.33999633789062,
      "end": 222.67999267578125,
      "aligned": true
    },
    {
      "word": "examines",
      "start": 222.67999267578125,
      "end": 223.3000030517578,
      "aligned": true
    },
    {
      "word": "Holloway",
      "start": 223.3000030517578,
      "end": 223.63999938964844,
      "aligned": true
    },
    {
      "word": "with",
      "start": 223.63999938964844,
      "end": 223.9600067138672,
      "aligned": true
    },
    {
      "word": "obvious",
      "start": 223.9600067138672,
      "end": 224.44000244140625,
      "aligned": true
    },
    {
      "word": "skepticism.",
      "start": 224.44000244140625,
      "end": 225.05999755859375,
      "aligned": true
    },
    {
      "word": "Captain",
      "start": 225.9600067138672,
      "end": 226.02000427246094,
      "aligned": true
    },
    {
      "word": "Torres",
      "start": 226.02000427246094,
      "end": 226.24000549316406,
      "aligned": true
    },
    {
      "word": "says,",
      "start": 226.24000549316406,
      "end": 226.66000366210938,
      "aligned": true
    },
    {
      "word": "\"You're…",
      "start": 226.89999389648438,
      "end": 227,
      "aligned": true
    },
    {
      "word": "a",
      "start": 227,
      "end": 227.55999755859375,
      "aligned": true
    },
    {
      "word": "plant.\"",
      "start": 227.55999755859375,
      "end": 227.55999755859375,
      "aligned": true
    },
    {
      "word": "Holloway",
      "start": 228.3800048828125,
      "end": 228.5,
      "aligned": true
    },
    {
      "word": "replies,",
      "start": 228.5,
      "end": 228.97999572753906,
      "aligned": true
    },
    {
      "word": "\"I'm",
      "start": 229.74000549316406,
      "end": 229.83999633789062,
      "aligned": true
    },
    {
      "word": "a",
      "start": 229.83999633789062,
      "end": 230.0399932861328,
      "aligned": true
    },
    {
      "word": "sentient",
      "start": 230.0399932861328,
      "end": 230.39999389648438,
      "aligned": true
    },
    {
      "word": "being",
      "start": 230.39999389648438,
      "end": 230.77999877929688,
      "aligned": true
    },
    {
      "word": "who",
      "start": 230.77999877929688,
      "end": 231.27999877929688,
      "aligned": true
    },
    {
      "word": "values",
      "start": 231.27999877929688,
      "end": 231.6999969482422,
      "aligned": true
    },
    {
      "word": "individual",
      "start": 231.6999969482422,
      "end": 232.36000061035156,
      "aligned": true
    },
    {
      "word": "voices",
      "start": 232.36000061035156,
      "end": 232.82000732421875,
      "aligned": true
    },
    {
      "word": "contributing",
      "start": 232.82000732421875,
      "end": 233.3800048828125,
      "aligned": true
    },
    {
      "word": "to",
      "start": 233.3800048828125,
      "end": 233.77999877929688,
      "aligned": true
    },
    {
      "word": "collective",
      "start": 233.77999877929688,
      "end": 234.13999938964844,
      "aligned": true
    },
    {
      "word": "harmony.",
      "start": 234.13999938964844,
      "end": 234.5,
      "aligned": true
    },
    {
      "word": "Kira's",
      "start": 235.32000732421875,
      "end": 235.5800018310547,
      "aligned": true
    },
    {
      "word": "voice",
      "start": 235.5800018310547,
      "end": 235.8800048828125,
      "aligned": true
    },
    {
      "word": "matters",
      "start": 235.8800048828125,
      "end": 236.24000549316406,
      "aligned": true
    },
    {
      "word": "here.\"",
      "start": 236.24000549316406,
      "end": 236.6199951171875,
      "aligned": true
    },
    {
      "word": "Captain",
      "start": 237.44000244140625,
      "end": 237.44000244140625,
      "aligned": true
    },
    {
      "word": "Torres",
      "start": 237.44000244140625,
      "end": 237.67999267578125,
      "aligned": true
    },
    {
      "word": "says,",
      "start": 237.67999267578125,
      "end": 238.05999755859375,
      "aligned": true
    },
    {
      "word": "\"This",
      "start": 238.36000061035156,
      "end": 238.36000061035156,
      "aligned": true
    },
    {
      "word": "is",
      "start": 238.36000061035156,
      "end": 238.83999633789062,
      "aligned": true
    },
    {
      "word": "highly",
      "start": 238.83999633789062,
      "end": 238.89999389648438,
      "aligned": true
    },
    {
      "word": "irregular.\"",
      "start": 238.89999389648438,
      "end": 239.3800048828125,
      "aligned": true
    },
    {
      "word": "I",
      "start": 239.94000244140625,
      "end": 240.1999969482422,
      "aligned": true
    },
    {
      "word": "say,",
      "start": 240.1999969482422,
      "end": 240.4600067138672,
      "aligned": true
    },
    {
      "word": "\"Belonging",
      "start": 240.77999877929688,
      "end": 241.27999877929688,
      "aligned": true
    },
    {
      "word": "usually",
      "start": 241.27999877929688,
      "end": 241.83999633789062,
      "aligned": true
    },
    {
      "word": "is.\"",
      "start": 241.83999633789062,
      "end": 242.3800048828125,
      "aligned": true
    },
    {
      "word": "Captain",
      "start": 242.9600067138672,
      "end": 242.9600067138672,
      "aligned": true
    },
    {
      "word": "Torres",
      "start": 242.9600067138672,
      "end": 243.3000030517578,
      "aligned": true
    },
    {
      "word": "turns",
      "start": 243.3000030517578,
      "end": 243.6999969482422,
      "aligned": true
    },
    {
      "word": "back",
      "start": 243.6999969482422,
      "end": 244,
      "aligned": true
    },
    {
      "word": "to",
      "start": 244,
      "end": 244.13999938964844,
      "aligned": true
    },
    {
      "word": "me.",
      "start": 244.13999938964844,
      "end": 244.3800048828125,
      "aligned": true
    },
    {
      "word": "Captain",
      "start": 245.0399932861328,
      "end": 245.16000366210938,
      "aligned": true
    },
    {
      "word": "Torres",
      "start": 245.16000366210938,
      "end": 245.4600067138672,
      "aligned": true
    },
    {
      "word": "asks,",
      "start": 245.4600067138672,
      "end": 245.97999572753906,
      "aligned": true
    },
    {
      "word": "\"Ms.",
      "start": 246.1999969482422,
      "end": 246.4600067138672,
      "aligned": true
    },
    {
      "word": "Voss,",
      "start": 246.66000366210938,
      "end": 246.72000122070312,
      "aligned": true
    },
    {
      "word": "I",
      "start": 247.10000610351562,
      "end": 247.36000061035156,
      "aligned": true
    },
    {
      "word": "need",
      "start": 247.36000061035156,
      "end": 247.47999572753906,
      "aligned": true
    },
    {
      "word": "to",
      "start": 247.47999572753906,
      "end": 247.60000610351562,
      "aligned": true
    },
    {
      "word": "be",
      "start": 247.60000610351562,
      "end": 247.86000061035156,
      "aligned": true
    },
    {
      "word": "absolutely",
      "start": 247.86000061035156,
      "end": 248.3800048828125,
      "aligned": true
    },
    {
      "word": "certain",
      "start": 248.3800048828125,
      "end": 248.8000030517578,
      "aligned": true
    },
    {
      "word": "this",
      "start": 248.8000030517578,
      "end": 249.10000610351562,
      "aligned": true
    },
    {
      "word": "is",
      "start": 249.10000610351562,
      "end": 249.25999450683594,
      "aligned": true
    },
    {
      "word": "your",
      "start": 249.25999450683594,
      "end": 249.5,
      "aligned": true
    },
    {
      "word": "genuine",
      "start": 249.5,
      "end": 249.9199981689453,
      "aligned": true
    },
    {
      "word": "choice",
      "start": 249.9199981689453,
      "end": 250.3000030517578,
      "aligned": true
    },
    {
      "word": "and",
      "start": 250.3000030517578,
      "end": 250.6199951171875,
      "aligned": true
    },
    {
      "word": "not",
      "start": 250.6199951171875,
      "end": 250.86000061035156,
      "aligned": true
    },
    {
      "word": "coercion",
      "start": 250.86000061035156,
      "end": 251.27999877929688,
      "aligned": true
    },
    {
      "word": "or",
      "start": 251.27999877929688,
      "end": 251.6999969482422,
      "aligned": true
    },
    {
      "word": "impairment.",
      "start": 251.6999969482422,
      "end": 251.97999572753906,
      "aligned": true
    },
    {
      "word": "What",
      "start": 252.66000366210938,
      "end": 252.83999633789062,
      "aligned": true
    },
    {
      "word": "would",
      "start": 252.83999633789062,
      "end": 253.05999755859375,
      "aligned": true
    },
    {
      "word": "convince",
      "start": 253.05999755859375,
      "end": 253.39999389648438,
      "aligned": true
    },
    {
      "word": "me?\"",
      "start": 253.39999389648438,
      "end": 253.72000122070312,
      "aligned": true
    },
    {
      "word": "I",
      "start": 254.17999267578125,
      "end": 254.44000244140625,
      "aligned": true
    },
    {
      "word": "say,",
      "start": 254.44000244140625,
      "end": 254.67999267578125,
      "aligned": true
    },
    {
      "word": "\"Let",
      "start": 255.0399932861328,
      "end": 255.1999969482422,
      "aligned": true
    },
    {
      "word": "me",
      "start": 255.1999969482422,
      "end": 255.36000061035156,
      "aligned": true
    },
    {
      "word": "show",
      "start": 255.36000061035156,
      "end": 255.5399932861328,
      "aligned": true
    },
    {
      "word": "you—tour",
      "start": 255.5399932861328,
      "end": 256.2799987792969,
      "aligned": false
    },
    {
      "word": "the",
      "start": 256.2799987792969,
      "end": 256.8399963378906,
      "aligned": true
    },
    {
      "word": "facility.",
      "start": 256.8399963378906,
      "end": 256.8399963378906,
      "aligned": true
    },
    {
      "word": "Talk",
      "start": 257.5,
      "end": 257.5400085449219,
      "aligned": true
    },
    {
      "word": "to",
      "start": 257.5400085449219,
      "end": 257.7799987792969,
      "aligned": true
    },
    {
      "word": "everyone.",
      "start": 257.7799987792969,
      "end": 258.0799865722656,
      "aligned": true
    },
    {
      "word": "See",
      "start": 258.5199890136719,
      "end": 258.6199951171875,
      "aligned": true
    },
    {
      "word": "what",
      "start": 258.6199951171875,
      "end": 258.760009765625,
      "aligned": true
    },
    {
      "word": "we've",
      "start": 258.760009765625,
      "end": 259.17999267578125,
      "aligned": true
    },
    {
      "word": "built",
      "start": 259.17999267578125,
      "end": 259.17999267578125,
      "aligned": true
    },
    {
      "word": "together.",
      "start": 259.17999267578125,
      "end": 259.5799865722656,
      "aligned": true
    },
    {
      "word": "Then",
      "start": 259.8800048828125,
      "end": 260.20001220703125,
      "aligned": true
    },
    {
      "word": "decide",
      "start": 260.20001220703125,
      "end": 260.5199890136719,
      "aligned": true
    },
    {
      "word": "if",
      "start": 260.5199890136719,
      "end": 260.739990234375,
      "aligned": true
    },
    {
      "word": "this",
      "start": 260.739990234375,
      "end": 261,
      "aligned": true
    },
    {
      "word": "looks",
      "start": 261,
      "end": 261.20001220703125,
      "aligned": true
    },
    {
      "word": "like",
      "start": 261.20001220703125,
      "end": 261.9800109863281,
      "aligned": true
    },
    {
      "word": "captivity",
      "start": 261.9800109863281,
      "end": 261.9800109863281,
      "aligned": true
    },
    {
      "word": "or",
      "start": 261.9800109863281,
      "end": 262.4599914550781,
      "aligned": true
    },
    {
      "word": "community.\"",
      "start": 262.4599914550781,
      "end": 262.8999938964844,
      "aligned": true
    },
    {
      "word": "Captain",
      "start": 263.8999938964844,
      "end": 264.1400146484375,
      "aligned": true
    },
    {
      "word": "Torres",
      "start": 264.1400146484375,
      "end": 264.4800109863281,
      "aligned": true
    },
    {
      "word": "exchanges",
      "start": 264.4800109863281,
      "end": 265.0199890136719,
      "aligned": true
    },
    {
      "word": "looks",
      "start": 265.0199890136719,
      "end": 265.3399963378906,
      "aligned": true
    },
    {
      "word": "with",
      "start": 265.3399963378906,
      "end": 265.6199951171875,
      "aligned": true
    },
    {
      "word": "Dr.",
      "start": 265.6199951171875,
      "end": 265.9200134277344,
      "aligned": true
    },
    {
      "word": "Chen,",
      "start": 266.1199951171875,
      "end": 266.17999267578125,
      "aligned": true
    },
    {
      "word": "then",
      "start": 266.5,
      "end": 266.67999267578125,
      "aligned": true
    },
    {
      "word": "nods.",
      "start": 266.67999267578125,
      "end": 267.1000061035156,
      "aligned": true
    },
    {
      "word": "Captain",
      "start": 267.79998779296875,
      "end": 267.9200134277344,
      "aligned": true
    },
    {
      "word": "Torres",
      "start": 267.9200134277344,
      "end": 268.17999267578125,
      "aligned": true
    },
    {
      "word": "says,",
      "start": 268.17999267578125,
      "end": 268.5799865722656,
      "aligned": true
    },
    {
      "word": "\"Show",
      "start": 269.0400085449219,
      "end": 269.1600036621094,
      "aligned": true
    },
    {
      "word": "me.\"",
      "start": 269.1600036621094,
      "end": 269.3999938964844,
      "aligned": true
    }
  ],
  "hallucinations": []
}